[   
        {
		"basepath" : "Cisco-IOS-XR-sysadmin-envmon-ui:envmon/environment/oper/current/location/sensor_attributes",
		"spec" : {
			"fields" : [
				{"name" : "location", "tag" : true},
				{"name" : "sensor", "tag": true},
				{
					"name" : "alarm",  
				        "fields" : [
   						{"name" : "value"}
					]

                                },
				{
					"name" : "sensor-id",  
				        "fields" : [
   						{"name" : "value","tag":true}
					]

                                },
				{
					"name" : "value",  
				        "fields" : [
   						{"name" : "value"}
					]

                                }



			]
		}
	},
	{
		"basepath" : "Cisco-IOS-XR-sysadmin-envmon-ui:envmon/environment/oper/temperatures/location/sensor_attributes",
		"spec" : {
			"fields" : [
				{"name" : "location", "tag" : true},
				{"name" : "sensor", "tag": true},
				{
					"name" : "alarm",  
				        "fields" : [
   						{"name" : "value"}
					]

                                },
                                {"name" : "critical-hi"},
				{"name" : "critical-lo"},
				{"name" : "major-hi"},
				{"name" : "major-lo"},
				{"name" : "minor-hi"},
				{"name" : "minor-lo"},
				{
					"name" : "sensor-id",  
				        "fields" : [
   						{"name" : "value"}
					]

                                },
				{
					"name" : "temperature-value",  
				        "fields" : [
   						{"name" : "value"}
					]

                                },
				{"name" : "value"}



			]
		}
	},
	{
		"basepath" : "Cisco-IOS-XR-sysadmin-envmon-ui:envmon/environment/oper/voltages/location/sensor_attributes",
		"spec" : {
			"fields" : [
				{"name" : "location", "tag" : true},
				{"name" : "sensor", "tag": true},
				{
					"name" : "alarm",  
				        "fields" : [
   						{"name" : "value"}
					]

                                },
                                {"name" : "critical-hi"},
				{"name" : "critical-lo"},
				{"name" : "major-hi"},
				{"name" : "major-lo"},
				{"name" : "minor-hi"},
				{"name" : "minor-lo"},
				{
					"name" : "sensor-id",  
				        "fields" : [
   						{"name" : "value"}
					]

                                },
				{
					"name" : "temperature-value",  
				        "fields" : [
   						{"name" : "value"}
					]

                                },
				{
					"name" : "value",  
				        "fields" : [
   						{"name" : "value"}
					]

                                }




			]
		}
	},
        {
		"basepath" : "Cisco-IOS-XR-sysadmin-envmon-ui:envmon/environment/oper/power/location/pem_attributes",
		"spec" : {
			"fields" : [
				{"name" : "location", "tag" : true},
				{"name" : "pem", "tag": true},
				{
					"name" : "pem-id",  
				        "fields" : [
   						{"name" : "value"}
					]

                                },
				{
					"name" : "card-type",  
				        "fields" : [
   						{"name" : "value"}
					]

                                },
				{
					"name" : "ps-type",  
				        "fields" : [
   						{"name" : "value"}
					]

                                },
				{"name" : "shelf-num"},
				
				
				{
					"name" : "supply-type",  
				        "fields" : [
   						{"name" : "value"}
					]

                                },
				{
					"name" : "input-voltage",  
				        "fields" : [
   						{"name" : "value"}
					]

                                },
				{
					"name" : "input-current",  
				        "fields" : [
   						{"name" : "value"}
					]

                                },
				{
					"name" : "output-voltage",  
				        "fields" : [
   						{"name" : "value"}
					]

                                },
				{
					"name" : "output-current",  
				        "fields" : [
   						{"name" : "value"}
					]

                                },
				{
					"name" : "status",  
				        "fields" : [
   						{"name" : "value"}
					]

                                },
				{
					"name" : "input-power-to-ps",  
				        "fields" : [
   						{"name" : "value"}
					]

                                },
				{
					"name" : "input-current-to-ps",  
				        "fields" : [
   						{"name" : "value"}
					]

                                },
				{
					"name" : "output-power-from-ps",  
				        "fields" : [
   						{"name" : "value"}
					]

                                },
					{
					"name" : "output-current-from-ps",  
				        "fields" : [
   						{"name" : "value"}
					]

                                },
				{"name" : "power-allocated"},
				{
					"name" : "power-consumed",  
				        "fields" : [
   						{"name" : "value"}
					]

                                },
				{
					"name" : "power-status",  
				        "fields" : [
   						{"name" : "value"}
					]

                                },
				{
					"name" : "confgd-power-redundancy-mode",  
				        "fields" : [
   						{"name" : "value"}
					]

                                },
				{"name" : "usable-power-capacity"},
				{"name" : "protection-power-capacity"},
				{"name" : "power-resrv-and-alloc"},
				{"name" : "system-power-used"},
				{"name" : "system-power-input"},
				{"name" : "power-level"},
				{"name" : "output-header"},
				{"name" : "output-footer"},
				{"name" : "ps-sum-footer"}


			]
		}
	},
	{
		"basepath" : "Cisco-IOS-XR-sysadmin-envmon-ui:envmon/environment/oper/fan/location/fan_attributes",
		"spec" : {
			"fields" : [
				{"name" : "location", "tag" : true},
				{"name" : "logical-slot", "tag": true},
				{
					"name" : "print-fan-header",  
				        "fields" : [
   						{"name" : "value"}
					]

                                },
				{
					"name" : "fru-pid",  
				        "fields" : [
   						{"name" : "value"}
					]

                                },
				{
					"name" : "fans-speed",  
				        "fields" : [
   						{"name" : "value"}
					]

                                },
				{"name" : "fan-header"},
				{
					"name" : "location",  
				        "fields" : [
   						{"name" : "value"}
					]

                                },
				{"name" : "speed-space"}

			]
		}
	},
	{
		"basepath" : "Cisco-IOS-XR-infra-statsd-oper:infra-statistics/interfaces/interface/latest/generic-counters",
		"spec" : {
			"fields" : [
				{"name" : "interface-name", "tag" : true},
				{"name" : "packets-received"},
				{"name" : "bytes-received"},
				{"name" : "packets-sent", "track": true},
				{"name" : "bytes-sent"},
				{"name" : "output-drops"},
				{"name" : "output-queue-drops"},
				{"name" : "input-drops"},
				{"name" : "input-queue-drops"},
				{"name" : "input-errors"},
				{"name" : "crc-errors"},
				{"name" : "input-ignored-packets"},
				{"name" : "output-errors"},
				{"name" : "output-buffer-failures"},
				{"name" : "carrier-transitions"}
			]
		}
	},
	{
		"basepath" : "Cisco-IOS-XR-mpls-te-oper:mpls-te/tunnels/tunnel-auto-bandwidths/tunnel-auto-bandwidth",
		"spec" : {
			"fields" : [
				{"name" : "tunnel-name", "tag" : true},
				{"name" : "highest-bandwidth"},
				{"name" : "last-sample-bandwidth"},
				{"name" : "samples-collected"},
				{"name" : "tunnel-requested-bandwidth"}
			]
		}
	},
	{
		"basepath" : "Cisco-IOS-XR-qos-ma-oper:qos/interface-table/interface/output/statistics",
		"spec" : {
			"fields" : [
				{"name" : "interface-name", "tag" : true},
				{"name" : "policy-name", "tag" : true},
				{
					"name" : "class-stats",
					"fields" : [
						{"name" : "class-name", "tag" : true},
						{
							"name" : "general-stats",
							"fields" : [
								{"name" : "transmit-packets"},
								{"name" : "transmit-bytes"},
								{"name" : "total-drop-packets"},
								{"name" : "total-drop-bytes"},
								{"name" : "total-drop-rate"},
								{"name" : "total-transmit-rate"}
							]
						},
						{
							"name" : "queue-stats-array",
							"fields" : [
								{"name" : "queue-id", "tag" : true},
								{"name" : "tail-drop-packets"},
								{"name" : "tail-drop-bytes"},
								{
									"name" : "queue-average-length",
									"fields" : [
										{"name" : "value"},
										{"name" : "unit", "tag" : true}
									]
								},
								{"name" : "random-drop-packets"},
								{"name" : "random-drop-bytes"},
								{"name" : "conform-packets"},
								{"name" : "conform-bytes"},
								{"name" : "exceed-packets"},
								{"name" : "exceed-bytes"}
							]
						}
					]
				}
			]
		}
	},
	{
		"basepath" : "Cisco-IOS-XR-procmem-oper:processes-memory/nodes/node/process-ids/process-id",
		"spec" : {
			"fields" : [
				{"name":"node-name", "tag": true},
				{"name":"name", "tag": true},
				{"name":"text-seg-size"},
				{"name":"data-seg-size"},
				{"name":"stack-seg-size"},
				{"name":"malloc-size"}
			]
		}
	},
	{
		"basepath" : "Cisco-IOS-XR-nto-misc-oper:memory-summary/nodes/node/summary",
		"spec" : {
			"fields" : [
				{"name":"node-name", "tag": true},
				{"name":"ram-memory"},
				{"name":"free-physical-memory"},
				{"name":"system-ram-memory"},
				{"name":"free-application-memory"}
			]
		}
	},
	{
		"basepath" : "Cisco-IOS-XR-wdsysmon-fd-oper:system-monitoring/cpu-utilization",
		"spec" : {
			"fields" : [
				{"name":"node-name", "tag": true},
				{"name":"total-cpu-one-minute"},
				{"name":"total-cpu-five-minute"},
				{"name":"total-cpu-fifteen-minute"},
				{
					"name":"process-cpu",
					"fields" : [
						{"name":"process-name", "tag": true},
						{"name":"process-cpu-one-minute"},
						{"name":"process-cpu-five-minute"},
						{"name":"process-cpu-fifteen-minute"}
					]
				}
			]
		}
	}
]
